LICENSE
README.md
setup.py
py_games/__init__.py
py_games.egg-info/PKG-INFO
py_games.egg-info/SOURCES.txt
py_games.egg-info/dependency_links.txt
py_games.egg-info/not-zip-safe
py_games.egg-info/requires.txt
py_games.egg-info/top_level.txt
py_games/games/PushTheBox.py
py_games/games/TIC_TAC_TOE.py
py_games/games/__init__.py
py_games/games/flappy.py
py_games/games/help.py
py_games/games/maze.py
py_games/games/pacman.py
py_games/games/snake.py